{"112":{"1121016":{"mjid":"1121016","name":"TEKNIK SIPIL","level":"S1","type":" SAINTEK ","quota":"109","registrant":{"2016":{"total":"486","admitted":"150(30.86%)","provinces":[{"11":385},{"12":84},{"13":12},{"14":0},{"15":0},{"16":0},{"17":1},{"18":1},{"19":1},{"21":0},{"31":1},{"32":1},{"35":0},{"36":0},{"73":0},{"52":0}]},"2017":{"total":"641","admitted":"120(18.72%)","provinces":[{"11":532},{"12":95},{"13":8},{"14":0},{"15":0},{"16":0},{"17":0},{"18":0},{"19":0},{"21":0},{"31":1},{"32":4},{"35":1},{"36":0},{"73":0},{"52":0}]},"2018":{"total":"724","admitted":"135(18.65%)","provinces":[{"11":526},{"12":164},{"13":20},{"14":4},{"15":4},{"16":2},{"17":0},{"18":0},{"19":0},{"21":1},{"31":0},{"32":0},{"35":0},{"36":3},{"73":0},{"52":0}]},"2019":{"total":"341","admitted":"124(36.36%)","provinces":[{"11":211},{"12":106},{"13":10},{"14":4},{"15":1},{"16":1},{"17":2},{"18":0},{"19":0},{"21":1},{"31":0},{"32":1},{"35":0},{"36":1},{"73":1},{"52":0}]},"2020":{"total":"263","admitted":"163(61.98%)","provinces":[{"11":168},{"12":77},{"13":15},{"14":1},{"15":1},{"16":1},{"17":0},{"18":0},{"19":0},{"21":0},{"31":0},{"32":0},{"35":0},{"36":0},{"73":0},{"52":0}]}}},"1121024":{"mjid":"1121024","name":"TEKNIK MESIN","level":"S1","type":" SAINTEK ","quota":"106","registrant":{"2016":{"total":"228","admitted":"120(52.63%)","provinces":[{"11":181},{"12":36},{"13":5},{"14":2},{"15":0},{"16":2},{"18":1},{"21":0},{"31":0},{"32":0},{"33":0},{"35":1},{"36":0},{"61":0},{"64":0},{"73":0}]},"2017":{"total":"327","admitted":"120(36.70%)","provinces":[{"11":268},{"12":49},{"13":6},{"14":0},{"15":0},{"16":1},{"18":0},{"21":0},{"31":0},{"32":3},{"33":0},{"35":0},{"36":0},{"61":0},{"64":0},{"73":0}]},"2018":{"total":"370","admitted":"138(37.30%)","provinces":[{"11":247},{"12":103},{"13":10},{"14":1},{"15":3},{"16":1},{"18":0},{"21":0},{"31":2},{"32":0},{"33":1},{"35":0},{"36":1},{"61":1},{"64":0},{"73":0}]},"2019":{"total":"206","admitted":"149(72.33%)","provinces":[{"11":111},{"12":78},{"13":10},{"14":2},{"15":0},{"16":0},{"18":0},{"21":0},{"31":1},{"32":1},{"33":0},{"35":0},{"36":0},{"61":0},{"64":1},{"73":1}]},"2020":{"total":"164","admitted":"164(100.00%)","provinces":[{"11":70},{"12":82},{"13":10},{"14":1},{"15":0},{"16":0},{"18":0},{"21":1},{"31":0},{"32":0},{"33":0},{"35":0},{"36":0},{"61":0},{"64":0},{"73":0}]}}},"1121032":{"mjid":"1121032","name":"TEKNIK KIMIA","level":"S1","type":" SAINTEK ","quota":"89","registrant":{"2016":{"total":"139","admitted":"100(71.94%)","provinces":[{"11":81},{"12":46},{"13":11},{"14":0},{"15":0},{"16":1},{"18":0},{"21":0},{"31":0},{"32":0},{"33":0},{"34":0},{"35":0},{"36":0},{"100":0}]},"2017":{"total":"256","admitted":"144(56.25%)","provinces":[{"11":129},{"12":90},{"13":25},{"14":3},{"15":0},{"16":1},{"18":0},{"21":0},{"31":3},{"32":2},{"33":0},{"34":1},{"35":0},{"36":2},{"100":0}]},"2018":{"total":"303","admitted":"159(52.48%)","provinces":[{"11":163},{"12":112},{"13":17},{"14":2},{"15":0},{"16":1},{"18":0},{"21":2},{"31":2},{"32":2},{"33":0},{"34":0},{"35":0},{"36":2},{"100":0}]},"2019":{"total":"245","admitted":"124(50.61%)","provinces":[{"11":99},{"12":123},{"13":13},{"14":2},{"15":1},{"16":1},{"18":1},{"21":1},{"31":1},{"32":1},{"33":0},{"34":1},{"35":0},{"36":0},{"100":0}]},"2020":{"total":"97","admitted":"149(153.61%)","provinces":[{"11":31},{"12":59},{"13":6},{"14":0},{"15":0},{"16":0},{"18":0},{"21":0},{"31":1},{"32":0},{"33":0},{"34":0},{"35":0},{"36":0},{"100":0}]}}},"1121047":{"mjid":"1121047","name":"TEKNIK ELEKTRO","level":"S1","type":" SAINTEK ","quota":"84","registrant":{"2016":{"total":"275","admitted":"120(43.64%)","provinces":[{"11":215},{"12":46},{"13":11},{"14":1},{"15":1},{"16":0},{"17":0},{"31":0},{"32":0},{"33":0},{"35":1},{"36":0},{"61":0},{"64":0},{"52":0}]},"2017":{"total":"333","admitted":"90(27.03%)","provinces":[{"11":285},{"12":43},{"13":5},{"14":0},{"15":0},{"16":0},{"17":0},{"31":0},{"32":0},{"33":0},{"35":0},{"36":0},{"61":0},{"64":0},{"52":0}]},"2018":{"total":"416","admitted":"134(32.21%)","provinces":[{"11":299},{"12":100},{"13":11},{"14":1},{"15":0},{"16":0},{"17":1},{"31":0},{"32":1},{"33":1},{"35":0},{"36":1},{"61":1},{"64":0},{"52":0}]},"2019":{"total":"261","admitted":"105(40.23%)","provinces":[{"11":160},{"12":82},{"13":14},{"14":2},{"15":0},{"16":1},{"17":0},{"31":0},{"32":0},{"33":0},{"35":0},{"36":2},{"61":0},{"64":0},{"52":0}]},"2020":{"total":"171","admitted":"117(68.42%)","provinces":[{"11":106},{"12":57},{"13":7},{"14":1},{"15":0},{"16":0},{"17":0},{"31":0},{"32":0},{"33":0},{"35":0},{"36":0},{"61":0},{"64":0},{"52":0}]}}},"1121055":{"mjid":"1121055","name":"TEKNIK INDUSTRI","level":"S1","type":" SAINTEK ","quota":"120","registrant":{"2016":{"total":"299","admitted":"120(40.13%)","provinces":[{"11":191},{"12":88},{"13":16},{"14":0},{"15":0},{"16":1},{"18":0},{"21":0},{"31":0},{"32":2},{"33":0},{"35":0},{"36":1}]},"2017":{"total":"493","admitted":"120(24.34%)","provinces":[{"11":331},{"12":143},{"13":11},{"14":1},{"15":0},{"16":2},{"18":0},{"21":0},{"31":2},{"32":2},{"33":0},{"35":0},{"36":1}]},"2018":{"total":"542","admitted":"122(22.51%)","provinces":[{"11":330},{"12":189},{"13":16},{"14":3},{"15":2},{"16":0},{"18":0},{"21":1},{"31":0},{"32":0},{"33":1},{"35":0},{"36":0}]},"2019":{"total":"326","admitted":"105(32.21%)","provinces":[{"11":169},{"12":140},{"13":11},{"14":0},{"15":1},{"16":1},{"18":0},{"21":1},{"31":0},{"32":0},{"33":0},{"35":2},{"36":1}]},"2020":{"total":"240","admitted":"139(57.92%)","provinces":[{"11":133},{"12":90},{"13":14},{"14":2},{"15":0},{"16":0},{"18":0},{"21":0},{"31":0},{"32":1},{"33":0},{"35":0},{"36":0}]}}},"1121063":{"mjid":"1121063","name":"TEKNIK INFORMATIKA","level":"S1","type":" SAINTEK ","quota":"157","registrant":{"2016":{"total":"822","admitted":"100(12.17%)","provinces":[{"11":731},{"12":83},{"13":4},{"14":1},{"15":1},{"16":0},{"17":0},{"18":0},{"21":0},{"31":1},{"32":0},{"33":0},{"35":0},{"36":0},{"63":0},{"73":1},{"82":0}]},"2017":{"total":"1090","admitted":"80(7.34%)","provinces":[{"11":988},{"12":93},{"13":5},{"14":1},{"15":0},{"16":0},{"17":0},{"18":0},{"21":0},{"31":1},{"32":1},{"33":0},{"35":0},{"36":0},{"63":1},{"73":0},{"82":0}]},"2018":{"total":"1331","admitted":"127(9.54%)","provinces":[{"11":1129},{"12":190},{"13":9},{"14":0},{"15":1},{"16":0},{"17":0},{"18":0},{"21":2},{"31":0},{"32":0},{"33":0},{"35":0},{"36":0},{"63":0},{"73":0},{"82":0}]},"2019":{"total":"558","admitted":"94(16.85%)","provinces":[{"11":457},{"12":85},{"13":6},{"14":1},{"15":0},{"16":1},{"17":0},{"18":0},{"21":1},{"31":0},{"32":2},{"33":1},{"35":1},{"36":1},{"63":0},{"73":1},{"82":1}]},"2020":{"total":"534","admitted":"138(25.84%)","provinces":[{"11":395},{"12":125},{"13":9},{"14":2},{"15":0},{"16":0},{"17":0},{"18":0},{"21":1},{"31":0},{"32":1},{"33":0},{"35":0},{"36":1},{"63":0},{"73":0},{"82":0}]}}},"1121071":{"mjid":"1121071","name":"TEKNIK ARSITEKTUR","level":"S1","type":" SAINTEK ","quota":"77","registrant":{"2016":{"total":"185","admitted":"60(32.43%)","provinces":[{"11":147},{"12":26},{"13":8},{"14":0},{"15":0},{"16":0},{"21":0},{"31":3},{"32":1},{"36":0},{"73":0},{"74":0}]},"2017":{"total":"276","admitted":"100(36.23%)","provinces":[{"11":215},{"12":51},{"13":4},{"14":2},{"15":0},{"16":0},{"21":0},{"31":2},{"32":2},{"36":0},{"73":0},{"74":0}]},"2018":{"total":"311","admitted":"97(31.19%)","provinces":[{"11":199},{"12":87},{"13":19},{"14":0},{"15":0},{"16":0},{"21":1},{"31":1},{"32":1},{"36":1},{"73":0},{"74":2}]},"2019":{"total":"166","admitted":"84(50.60%)","provinces":[{"11":88},{"12":58},{"13":14},{"14":3},{"15":0},{"16":0},{"21":0},{"31":0},{"32":1},{"36":0},{"73":2},{"74":0}]},"2020":{"total":"113","admitted":"108(95.58%)","provinces":[{"11":72},{"12":30},{"13":9},{"14":0},{"15":0},{"16":0},{"21":0},{"31":0},{"32":2},{"36":0},{"73":0},{"74":0}]}}},"1121086":{"mjid":"1121086","name":"AGROEKOTEKNOLOGI","level":"S1","type":" SAINTEK ","quota":"104","registrant":{"2016":{"total":"475","admitted":"120(25.26%)","provinces":[{"11":273},{"12":165},{"13":32},{"14":2},{"16":0},{"17":0},{"18":0},{"31":0},{"32":2},{"33":0},{"36":1},{"100":0}]},"2017":{"total":"491","admitted":"100(20.37%)","provinces":[{"11":302},{"12":170},{"13":17},{"14":1},{"16":0},{"17":1},{"18":0},{"31":0},{"32":0},{"33":0},{"36":0},{"100":0}]},"2018":{"total":"515","admitted":"132(25.63%)","provinces":[{"11":259},{"12":244},{"13":9},{"14":0},{"16":1},{"17":0},{"18":0},{"31":0},{"32":1},{"33":1},{"36":0},{"100":0}]},"2019":{"total":"302","admitted":"95(31.46%)","provinces":[{"11":119},{"12":175},{"13":4},{"14":3},{"16":0},{"17":0},{"18":0},{"31":0},{"32":0},{"33":0},{"36":0},{"100":0}]},"2020":{"total":"247","admitted":"132(53.44%)","provinces":[{"11":71},{"12":163},{"13":11},{"14":1},{"16":0},{"17":0},{"18":1},{"31":0},{"32":0},{"33":0},{"36":0},{"100":0}]}}},"1121094":{"mjid":"1121094","name":"AGRIBISNIS","level":"S1","type":" SAINTEK ","quota":"66","registrant":{"2016":{"total":"598","admitted":"100(16.72%)","provinces":[{"11":458},{"12":125},{"13":13},{"14":1},{"15":0},{"16":1},{"18":0},{"31":0},{"32":0},{"35":0},{"36":0},{"53":0},{"91":0}]},"2017":{"total":"738","admitted":"60(8.13%)","provinces":[{"11":533},{"12":194},{"13":7},{"14":0},{"15":0},{"16":1},{"18":0},{"31":0},{"32":2},{"35":0},{"36":0},{"53":1},{"91":0}]},"2018":{"total":"780","admitted":"70(8.97%)","provinces":[{"11":507},{"12":257},{"13":9},{"14":1},{"15":4},{"16":0},{"18":0},{"31":0},{"32":0},{"35":1},{"36":1},{"53":0},{"91":0}]},"2019":{"total":"364","admitted":"74(20.33%)","provinces":[{"11":207},{"12":149},{"13":6},{"14":0},{"15":0},{"16":0},{"18":0},{"31":0},{"32":0},{"35":1},{"36":0},{"53":0},{"91":0}]},"2020":{"total":"187","admitted":"68(36.36%)","provinces":[{"11":88},{"12":98},{"13":0},{"14":0},{"15":0},{"16":0},{"18":1},{"31":0},{"32":0},{"35":0},{"36":0},{"53":0},{"91":0}]}}},"1121105":{"mjid":"1121105","name":"AKUAKULTUR","level":"S1","type":" SAINTEK ","quota":"19","registrant":{"2016":{"total":"236","admitted":"80(33.90%)","provinces":[{"11":188},{"12":46},{"13":1},{"14":0},{"16":0},{"18":1},{"19":0},{"31":0},{"32":0},{"36":0}]},"2017":{"total":"240","admitted":"79(32.92%)","provinces":[{"11":184},{"12":46},{"13":6},{"14":0},{"16":0},{"18":0},{"19":1},{"31":0},{"32":3},{"36":0}]},"2018":{"total":"254","admitted":"75(29.53%)","provinces":[{"11":178},{"12":68},{"13":7},{"14":0},{"16":0},{"18":0},{"19":0},{"31":0},{"32":0},{"36":1}]},"2019":{"total":"90","admitted":"61(67.78%)","provinces":[{"11":47},{"12":41},{"13":0},{"14":2},{"16":0},{"18":0},{"19":0},{"31":0},{"32":0},{"36":0}]},"2020":{"total":"24","admitted":"47(195.83%)","provinces":[{"11":12},{"12":11},{"13":1},{"14":0},{"16":0},{"18":0},{"19":0},{"31":0},{"32":0},{"36":0}]}}},"1121113":{"mjid":"1121113","name":"KEDOKTERAN","level":"S1","type":" SAINTEK ","quota":"30","registrant":{"2016":{"total":"1042","admitted":"16(1.54%)","provinces":[{"11":596},{"12":299},{"13":79},{"14":8},{"15":5},{"16":5},{"17":2},{"18":3},{"19":1},{"21":2},{"31":7},{"32":17},{"33":1},{"34":2},{"35":3},{"36":7},{"61":1},{"62":0},{"63":0},{"64":0},{"65":0},{"71":1},{"72":0},{"73":1},{"74":0},{"52":1},{"81":0},{"91":0},{"92":1},{"100":0}]},"2017":{"total":"1117","admitted":"25(2.24%)","provinces":[{"11":641},{"12":319},{"13":83},{"14":24},{"15":5},{"16":3},{"17":3},{"18":0},{"19":1},{"21":2},{"31":8},{"32":18},{"33":0},{"34":1},{"35":1},{"36":6},{"61":0},{"62":0},{"63":0},{"64":1},{"65":0},{"71":0},{"72":0},{"73":0},{"74":1},{"52":0},{"81":0},{"91":0},{"92":0},{"100":0}]},"2018":{"total":"1243","admitted":"32(2.57%)","provinces":[{"11":602},{"12":406},{"13":117},{"14":30},{"15":9},{"16":10},{"17":3},{"18":5},{"19":2},{"21":4},{"31":17},{"32":23},{"33":3},{"34":0},{"35":1},{"36":10},{"61":0},{"62":0},{"63":0},{"64":0},{"65":0},{"71":0},{"72":0},{"73":1},{"74":0},{"52":0},{"81":0},{"91":0},{"92":0},{"100":0}]},"2019":{"total":"932","admitted":"32(3.43%)","provinces":[{"11":382},{"12":316},{"13":101},{"14":28},{"15":6},{"16":4},{"17":3},{"18":4},{"19":0},{"21":2},{"31":13},{"32":37},{"33":4},{"34":1},{"35":7},{"36":14},{"61":0},{"62":0},{"63":0},{"64":0},{"65":0},{"71":0},{"72":0},{"73":4},{"74":0},{"52":0},{"81":0},{"91":2},{"92":1},{"100":0}]},"2020":{"total":"944","admitted":"36(3.81%)","provinces":[{"11":446},{"12":321},{"13":89},{"14":21},{"15":3},{"16":5},{"17":2},{"18":4},{"19":1},{"21":6},{"31":5},{"32":26},{"33":0},{"34":0},{"35":1},{"36":7},{"61":2},{"62":0},{"63":0},{"64":1},{"65":1},{"71":0},{"72":1},{"73":0},{"74":0},{"52":1},{"81":1},{"91":0},{"92":0},{"100":0}]}}},"1121121":{"mjid":"1121121","name":"PENDIDIKAN FISIKA","level":"S1","type":" SAINTEK ","quota":"17","registrant":{"2016":{"total":"85","admitted":"50(58.82%)","provinces":[{"11":76},{"12":8},{"13":1},{"14":0}]},"2017":{"total":"108","admitted":"40(37.04%)","provinces":[{"11":93},{"12":14},{"13":1},{"14":0}]},"2018":{"total":"79","admitted":"56(70.89%)","provinces":[{"11":60},{"12":17},{"13":1},{"14":1}]},"2019":{"total":"122","admitted":"67(54.92%)","provinces":[{"11":81},{"12":40},{"13":1},{"14":0}]},"2020":{"total":"20","admitted":"59(295.00%)","provinces":[{"11":12},{"12":7},{"13":0},{"14":1}]}}},"1121136":{"mjid":"1121136","name":"PENDIDIKAN KIMIA","level":"S1","type":" SAINTEK ","quota":"21","registrant":{"2016":{"total":"101","admitted":"50(49.50%)","provinces":[{"11":78},{"12":17},{"13":4},{"16":1},{"18":0},{"19":1},{"21":0},{"32":0}]},"2017":{"total":"100","admitted":"48(48.00%)","provinces":[{"11":81},{"12":18},{"13":0},{"16":0},{"18":0},{"19":0},{"21":0},{"32":1}]},"2018":{"total":"76","admitted":"53(69.74%)","provinces":[{"11":55},{"12":20},{"13":1},{"16":0},{"18":0},{"19":0},{"21":0},{"32":0}]},"2019":{"total":"109","admitted":"46(42.20%)","provinces":[{"11":68},{"12":34},{"13":4},{"16":1},{"18":1},{"19":0},{"21":0},{"32":0}]},"2020":{"total":"26","admitted":"64(246.15%)","provinces":[{"11":16},{"12":10},{"13":0},{"16":0},{"18":0},{"19":0},{"21":0},{"32":0}]}}},"1121144":{"mjid":"1121144","name":"PENDIDIKAN MATEMATIKA","level":"S1","type":" SAINTEK ","quota":"49","registrant":{"2016":{"total":"167","admitted":"50(29.94%)","provinces":[{"11":131},{"12":31},{"13":4},{"14":0},{"21":1},{"31":0},{"36":0}]},"2017":{"total":"176","admitted":"40(22.73%)","provinces":[{"11":144},{"12":32},{"13":0},{"14":0},{"21":0},{"31":0},{"36":0}]},"2018":{"total":"159","admitted":"45(28.30%)","provinces":[{"11":110},{"12":45},{"13":3},{"14":0},{"21":0},{"31":0},{"36":1}]},"2019":{"total":"114","admitted":"40(35.09%)","provinces":[{"11":80},{"12":32},{"13":1},{"14":1},{"21":0},{"31":0},{"36":0}]},"2020":{"total":"57","admitted":"68(119.30%)","provinces":[{"11":30},{"12":22},{"13":4},{"14":0},{"21":0},{"31":1},{"36":0}]}}},"1121152":{"mjid":"1121152","name":"PENDIDIKAN VOKASIONAL TEKNIK MESIN","level":"S1","type":" SAINTEK ","quota":"15","registrant":{"2016":{"total":"86","admitted":"50(58.14%)","provinces":[{"11":75},{"12":8},{"13":2},{"14":1},{"15":0},{"35":0}]},"2017":{"total":"92","admitted":"55(59.78%)","provinces":[{"11":85},{"12":7},{"13":0},{"14":0},{"15":0},{"35":0}]},"2018":{"total":"102","admitted":"55(53.92%)","provinces":[{"11":74},{"12":23},{"13":4},{"14":0},{"15":1},{"35":0}]},"2019":{"total":"25","admitted":"49(196.00%)","provinces":[{"11":22},{"12":3},{"13":0},{"14":0},{"15":0},{"35":0}]},"2020":{"total":"12","admitted":"27(225.00%)","provinces":[{"11":9},{"12":2},{"13":0},{"14":1},{"15":0},{"35":0}]}}},"1121167":{"mjid":"1121167","name":"SISTEM INFORMASI","level":"S1","type":" SAINTEK ","quota":"101","registrant":{"2016":{"total":"219","admitted":"50(22.83%)","provinces":[{"11":173},{"12":35},{"13":11},{"14":0},{"15":0},{"16":0},{"17":0},{"21":0},{"31":0},{"32":0},{"33":0},{"35":0},{"36":0}]},"2017":{"total":"273","admitted":"60(21.98%)","provinces":[{"11":225},{"12":41},{"13":6},{"14":0},{"15":0},{"16":1},{"17":0},{"21":0},{"31":0},{"32":0},{"33":0},{"35":0},{"36":0}]},"2018":{"total":"391","admitted":"78(19.95%)","provinces":[{"11":258},{"12":108},{"13":21},{"14":0},{"15":0},{"16":0},{"17":1},{"21":0},{"31":0},{"32":0},{"33":2},{"35":0},{"36":1}]},"2019":{"total":"393","admitted":"69(17.56%)","provinces":[{"11":267},{"12":107},{"13":10},{"14":1},{"15":0},{"16":0},{"17":0},{"21":0},{"31":2},{"32":0},{"33":0},{"35":1},{"36":1}]},"2020":{"total":"236","admitted":"105(44.49%)","provinces":[{"11":147},{"12":80},{"13":6},{"14":2},{"15":1},{"16":0},{"17":0},{"21":0},{"31":0},{"32":0},{"33":0},{"35":0},{"36":0}]}}},"1121175":{"mjid":"1121175","name":"ILMU KELAUTAN","level":"S1","type":" SAINTEK ","quota":"19","registrant":{"2016":{"total":" - ","admitted":" - (nan%)","provinces":[{"11":0},{"12":0},{"13":0},{"14":0},{"16":0},{"21":0},{"31":0},{"32":0},{"36":0}]},"2017":{"total":"167","admitted":"63(37.72%)","provinces":[{"11":123},{"12":40},{"13":1},{"14":0},{"16":1},{"21":0},{"31":0},{"32":1},{"36":1}]},"2018":{"total":"161","admitted":"58(36.02%)","provinces":[{"11":120},{"12":33},{"13":4},{"14":0},{"16":0},{"21":0},{"31":1},{"32":1},{"36":2}]},"2019":{"total":"83","admitted":"55(66.27%)","provinces":[{"11":40},{"12":38},{"13":0},{"14":1},{"16":0},{"21":1},{"31":1},{"32":1},{"36":1}]},"2020":{"total":"54","admitted":"36(66.67%)","provinces":[{"11":29},{"12":22},{"13":3},{"14":0},{"16":0},{"21":0},{"31":0},{"32":0},{"36":0}]}}},"1121183":{"mjid":"1121183","name":"TEKNIK MATERIAL","level":"S1","type":" SAINTEK ","quota":"6","registrant":{"2016":{"total":" - ","admitted":" - (nan%)","provinces":[{"11":0},{"12":0},{"13":0},{"73":0}]},"2017":{"total":" - ","admitted":" - (nan%)","provinces":[{"11":0},{"12":0},{"13":0},{"73":0}]},"2018":{"total":" - ","admitted":" - (nan%)","provinces":[{"11":0},{"12":0},{"13":0},{"73":0}]},"2019":{"total":"103","admitted":"55(53.40%)","provinces":[{"11":57},{"12":39},{"13":5},{"73":2}]},"2020":{"total":"24","admitted":"55(229.17%)","provinces":[{"11":15},{"12":9},{"13":0},{"73":0}]}}},"1121191":{"mjid":"1121191","name":"TEKNIK LOGISTIK","level":"S1","type":" SAINTEK ","quota":"20","registrant":{"2016":{"total":" - ","admitted":" - (nan%)"},"2017":{"total":" - ","admitted":" - (nan%)"},"2018":{"total":" - ","admitted":" - (nan%)"},"2019":{"total":" - ","admitted":" - (nan%)"},"2020":{"total":" - ","admitted":" - (nan%)"}}},"ucid":"112","name":"UNIVERSITAS TEUKU UMAR"}}
